bicorne_bank/__init__.py
bicorne_bank-0.0.0.dist-info/METADATA
bicorne_bank-0.0.0.dist-info/WHEEL
bicorne_bank-0.0.0.dist-info/license.txt
bicorne_bank-0.0.0.dist-info/top_level.txt
bicorne_bank-0.0.0.dist-info/RECORD
